fastmcp_mount/__init__.py
fastmcp_mount/middleware.py
fastmcp_mount/py.typed
fastmcp_mount-0.1.0.dist-info/licenses/LICENSE
fastmcp_mount-0.1.0.dist-info/METADATA
fastmcp_mount-0.1.0.dist-info/WHEEL
fastmcp_mount-0.1.0.dist-info/top_level.txt
fastmcp_mount-0.1.0.dist-info/RECORD
