Metadata-Version: 2.4
Name: fastmcp-mount
Version: 0.1.0
Summary: ASGI Middleware to fix FastMCP endpoint paths when mounted under a sub-path.
Author-email: Dwayn Matthies <dwayn.matthies@gmail.com>
License: MIT License
Project-URL: Homepage, https://github.com/dwayn/fastmcp-mount
Project-URL: Repository, https://github.com/dwayn/fastmcp-mount
Project-URL: Issues, https://github.com/dwayn/fastmcp-mount/issues
Keywords: asgi,middleware,fastmcp,mcp,sse,fastapi,starlette,mount,subpath,path,fix
Classifier: Development Status :: 4 - Beta
Classifier: Framework :: AsyncIO
Classifier: Framework :: FastAPI
Classifier: Intended Audience :: Developers
Classifier: License :: OSI Approved :: MIT License
Classifier: Operating System :: OS Independent
Classifier: Programming Language :: Python :: 3
Classifier: Programming Language :: Python :: 3.8
Classifier: Programming Language :: Python :: 3.9
Classifier: Programming Language :: Python :: 3.10
Classifier: Programming Language :: Python :: 3.11
Classifier: Programming Language :: Python :: 3.12
Classifier: Topic :: Internet :: WWW/HTTP :: WSGI :: Middleware
Classifier: Topic :: Software Development :: Libraries :: Python Modules
Classifier: Typing :: Typed
Requires-Python: >=3.8
License-File: LICENSE
Requires-Dist: starlette>=0.30.0
Provides-Extra: test
Requires-Dist: pytest>=7.0.0; extra == "test"
Requires-Dist: pytest-asyncio>=0.18.0; extra == "test"
Requires-Dist: httpx>=0.25.0; extra == "test"
Requires-Dist: uvicorn[standard]>=0.20.0; extra == "test"
Provides-Extra: dev
Requires-Dist: fastmcp-mount[test]; extra == "dev"
Requires-Dist: ruff>=0.1.0; extra == "dev"
Requires-Dist: build>=0.10.0; extra == "dev"
Requires-Dist: twine>=4.0.0; extra == "dev"
Requires-Dist: mypy>=1.0.0; extra == "dev"
Dynamic: license-file
